ezvi/__init__.py
ezvi/cli.py
ezvi/funcmodule.py
ezvi/human_typing.py
ezvi/tools.py
ezvi-0.1.7.dist-info/entry_points.txt
ezvi-0.1.7.dist-info/LICENSE
ezvi-0.1.7.dist-info/WHEEL
ezvi-0.1.7.dist-info/METADATA
ezvi-0.1.7.dist-info/RECORD
