Metadata-Version: 2.1
Name: ezvi
Version: 0.1.7
Summary: Automated typing in the Vi editor.
License: MIT
Author: TrickyTroll
Author-email: tricky@beon.ca
Requires-Python: >=3.7,<4.0
Classifier: Development Status :: 3 - Alpha
Classifier: License :: OSI Approved :: MIT License
Classifier: Natural Language :: English
Classifier: Operating System :: POSIX
Classifier: Programming Language :: Python :: 3
Classifier: Programming Language :: Python :: 3.10
Classifier: Programming Language :: Python :: 3.7
Classifier: Programming Language :: Python :: 3.8
Classifier: Programming Language :: Python :: 3.9
Requires-Dist: PyYAML (>=6.0,<7.0)
Requires-Dist: astroid (==2.4.2)
Requires-Dist: click (==7.1.2)
Requires-Dist: isort (==5.6.4)
Requires-Dist: lazy-object-proxy (==1.4.3)
Requires-Dist: mccabe (==0.6.1)
Requires-Dist: pylint (==2.6.0)
Requires-Dist: six (==1.15.0)
Requires-Dist: toml (==0.10.2)
